{"name":"feColorMatrix","status":"living","summary":"The `<feColorMatrix>` SVG filter element changes colors based on a transformation matrix. Every pixel's color value `[R,G,B,A]` is matrix multiplied by a 5 by 5 color matrix to create new color `[R',G',B',A']`.","url":"https://developer.mozilla.org/en-US/docs/Web/SVG/Element/feColorMatrix","type":"element","scope":"SVG","tags":["SVG","SVG Filter"],"interfaces":["SVGFEColorMatrixElement","SVGElement","Element"],"namespace":"http://www.w3.org/2000/svg","contentCategories":"","permittedContent":"","tagOmission":"","permittedParents":"","implicitAriaRole":"","permittedAriaRoles":"","globalAttributes":"https://mdn-element-api.netlify.com/svg/_global-attributes.json","attributes":{}}
